mongofw/__init__.py
mongofw/utils.py
mongofw-1.0.1.dist-info/licenses/LICENSE
mongofw-1.0.1.dist-info/METADATA
mongofw-1.0.1.dist-info/WHEEL
mongofw-1.0.1.dist-info/top_level.txt
mongofw-1.0.1.dist-info/RECORD
