Metadata-Version: 2.4
Name: mongofw
Version: 1.0.1
Summary: Python + Mongo
Home-page: https://github.com/muslu/mongofw
Author: Muslu Yüksektepe (musluyuksektepe@gmail.com)
Author-email: musluyuksektepe@gmail.com
Classifier: Programming Language :: Python :: 3
Classifier: License :: OSI Approved :: MIT License
Classifier: Operating System :: OS Independent
Requires-Python: >=3.9
License-File: LICENSE
Requires-Dist: pymongo
Dynamic: author
Dynamic: author-email
Dynamic: classifier
Dynamic: description-content-type
Dynamic: home-page
Dynamic: license-file
Dynamic: requires-dist
Dynamic: requires-python
Dynamic: summary
